Metadata-Version: 2.1
Name: socketmaxrskiy
Version: 1.0
Summary: Socket for python.
Home-page: UNKNOWN
Author-email: maxrskiy@mail.ru
License: UNKNOWN
Platform: UNKNOWN
